LICENSE
MANIFEST.in
README.md
setup.cfg
setup.py
ridi_django_oauth2/__init__.py
ridi_django_oauth2/config.py
ridi_django_oauth2/constants.py
ridi_django_oauth2/decorators.py
ridi_django_oauth2/exceptions.py
ridi_django_oauth2/managers.py
ridi_django_oauth2/middlewares.py
ridi_django_oauth2/models.py
ridi_django_oauth2/response.py
ridi_django_oauth2.egg-info/PKG-INFO
ridi_django_oauth2.egg-info/SOURCES.txt
ridi_django_oauth2.egg-info/dependency_links.txt
ridi_django_oauth2.egg-info/requires.txt
ridi_django_oauth2.egg-info/top_level.txt
ridi_django_oauth2/migrations/0001_initial.py
ridi_django_oauth2/migrations/0002_auto_20180322_1157.py
ridi_django_oauth2/migrations/__init__.py
ridi_django_oauth2/rest_framework/__init__.py
ridi_django_oauth2/rest_framework/authentication.py
ridi_django_oauth2/utils/__init__.py
ridi_django_oauth2/utils/cookie.py
ridi_django_oauth2/utils/token.py
ridi_django_oauth2_lib/__init__.py
ridi_django_oauth2_lib/decorators/__init__.py
ridi_django_oauth2_lib/decorators/retry.py
ridi_django_oauth2_lib/utils/__init__.py
ridi_django_oauth2_lib/utils/bytes.py
ridi_oauth2/__init__.py
ridi_oauth2/client/__init__.py
ridi_oauth2/client/constants.py
ridi_oauth2/client/dtos.py
ridi_oauth2/client/exceptions.py
ridi_oauth2/client/grant.py
ridi_oauth2/common/__init__.py
ridi_oauth2/common/constants.py
ridi_oauth2/common/utils/__init__.py
ridi_oauth2/common/utils/string.py
ridi_oauth2/introspector/__init__.py
ridi_oauth2/introspector/base.py
ridi_oauth2/introspector/constants.py
ridi_oauth2/introspector/dtos.py
ridi_oauth2/introspector/exceptions.py
ridi_oauth2/introspector/factories.py
ridi_oauth2/introspector/helpers.py
ridi_oauth2/introspector/key_handler.py
ridi_oauth2/resource/__init__.py
ridi_oauth2/resource/constants.py
ridi_oauth2/resource/scope_checker.py