Metadata-Version: 1.1
Name: ridi-django-oauth2
Version: 1.0.7
Summary: RIDI Django OAuth2 Library
Home-page: https://github.com/ridi/django-oauth2
Author: UNKNOWN
Author-email: UNKNOWN
License: MIT
Keywords: oauth2,oauth2-resource,ridi,ridibooks
Platform: UNKNOWN
Classifier: Development Status :: 3 - Alpha
Classifier: Intended Audience :: Developers
Classifier: License :: OSI Approved :: MIT License
Classifier: Framework :: Django :: 2.0
Classifier: Programming Language :: Python :: 3.6
